{
  "collectionName": "components_blocks_cta_buttons",
  "info": {
    "displayName": "CTA Button",
    "icon": "cursor",
    "description": "Botón de call to action"
  },
  "options": {},
  "attributes": {
    "text": {
      "type": "string",
      "required": true
    },
    "link": {
      "type": "string",
      "required": true
    },
    "style": {
      "type": "enumeration",
      "enum": ["primary", "secondary", "outline", "ghost"],
      "default": "primary",
      "required": true
    },
    "openInNewTab": {
      "type": "boolean",
      "default": false
    }
  }
}
